pymeasure/__init__.py
pymeasure/console.py
pymeasure/errors.py
pymeasure/generator.py
pymeasure/log.py
pymeasure/process.py
pymeasure/test.py
pymeasure/thread.py
pymeasure/units.py
pymeasure/adapters/__init__.py
pymeasure/adapters/adapter.py
pymeasure/adapters/prologix.py
pymeasure/adapters/protocol.py
pymeasure/adapters/serial.py
pymeasure/adapters/telnet.py
pymeasure/adapters/visa.py
pymeasure/adapters/vxi11.py
pymeasure/display/Qt.py
pymeasure/display/__init__.py
pymeasure/display/browser.py
pymeasure/display/console.py
pymeasure/display/curves.py
pymeasure/display/inputs.py
pymeasure/display/listeners.py
pymeasure/display/log.py
pymeasure/display/manager.py
pymeasure/display/plotter.py
pymeasure/display/thread.py
pymeasure/display/widgets/__init__.py
pymeasure/display/widgets/browser_widget.py
pymeasure/display/widgets/directory_widget.py
pymeasure/display/widgets/dock_widget.py
pymeasure/display/widgets/estimator_widget.py
pymeasure/display/widgets/fileinput_widget.py
pymeasure/display/widgets/filename_widget.py
pymeasure/display/widgets/image_frame.py
pymeasure/display/widgets/image_widget.py
pymeasure/display/widgets/inputs_widget.py
pymeasure/display/widgets/log_widget.py
pymeasure/display/widgets/plot_frame.py
pymeasure/display/widgets/plot_widget.py
pymeasure/display/widgets/results_dialog.py
pymeasure/display/widgets/sequencer_widget.py
pymeasure/display/widgets/tab_widget.py
pymeasure/display/widgets/table_widget.py
pymeasure/display/windows/__init__.py
pymeasure/display/windows/managed_dock_window.py
pymeasure/display/windows/managed_image_window.py
pymeasure/display/windows/managed_window.py
pymeasure/display/windows/plotter_window.py
pymeasure/experiment/__init__.py
pymeasure/experiment/config.py
pymeasure/experiment/experiment.py
pymeasure/experiment/listeners.py
pymeasure/experiment/parameters.py
pymeasure/experiment/procedure.py
pymeasure/experiment/results.py
pymeasure/experiment/sequencer.py
pymeasure/experiment/workers.py
PyMeasure-0.14.0.dist-info/LICENSE.txt
PyMeasure-0.14.0.dist-info/METADATA
PyMeasure-0.14.0.dist-info/WHEEL
PyMeasure-0.14.0.dist-info/top_level.txt
PyMeasure-0.14.0.dist-info/RECORD
