Metadata-Version: 2.1
Name: PyMeasure
Version: 0.14.0
Summary: Scientific measurement library for instruments, experiments, and live-plotting
Home-page: https://github.com/pymeasure/pymeasure
Author: PyMeasure Developers
License: MIT
Keywords: measure,instrument,experiment control,automate,graph,plot
Classifier: Development Status :: 4 - Beta
Classifier: Intended Audience :: Science/Research
Classifier: License :: OSI Approved :: MIT License
Classifier: Operating System :: MacOS
Classifier: Operating System :: Microsoft :: Windows
Classifier: Operating System :: POSIX
Classifier: Operating System :: Unix
Classifier: Programming Language :: Python :: 3 :: Only
Classifier: Programming Language :: Python :: 3.8
Classifier: Programming Language :: Python :: 3.9
Classifier: Programming Language :: Python :: 3.10
Classifier: Programming Language :: Python :: 3.11
Classifier: Programming Language :: Python :: 3.12
Classifier: Topic :: Scientific/Engineering
Requires-Python: >=3.8
License-File: LICENSE.txt
Requires-Dist: numpy <3,>=1.6.1
Requires-Dist: pandas <3,>=0.14
Requires-Dist: pint
Requires-Dist: pyvisa >=1.9
Requires-Dist: pyserial >=2.7
Requires-Dist: pyqtgraph >=0.12
Requires-Dist: importlib-metadata ; python_version < "3.8"
Provides-Extra: python-vxi11
Requires-Dist: python-vxi11 >=0.9 ; extra == 'python-vxi11'
Provides-Extra: tcp
Requires-Dist: pyzmq >=16.0.2 ; extra == 'tcp'
Requires-Dist: cloudpickle >=0.3.1 ; extra == 'tcp'
Provides-Extra: tests
Requires-Dist: pytest >=3.3.0 ; extra == 'tests'
Requires-Dist: pytest-cov >=4.1.0 ; extra == 'tests'
Requires-Dist: pytest-qt >=2.4.0 ; extra == 'tests'
Requires-Dist: pyvisa-sim >=0.4.0 ; extra == 'tests'
